mc_server_tool/__init__.py
mc_server_tool/src/__init__.py
mc_server_tool/src/arguments.py
mc_server_tool/src/common.py
mc_server_tool/src/downloads.py
mc_server_tool/src/execute.py
mc_server_tool/src/globals.py
mc_server_tool/src/menu.py
mc_server_tool-0.0.9.dist-info/METADATA
mc_server_tool-0.0.9.dist-info/WHEEL
mc_server_tool-0.0.9.dist-info/entry_points.txt
mc_server_tool-0.0.9.dist-info/licenses/LICENSE
mc_server_tool-0.0.9.dist-info/RECORD
