Metadata-Version: 2.4
Name: mc-server-tool
Version: 0.0.9
Summary: A minecraft server installer!
Project-URL: Homepage, https://github.com/Tmaster055/Minecraft-Server-Installer
Project-URL: Issues, https://github.com/Tmaster055/Minecraft-Server-Installer/issues
Author: Tmaster055
License-File: LICENSE
Classifier: License :: OSI Approved :: MIT License
Classifier: Operating System :: OS Independent
Classifier: Programming Language :: Python :: 3
Requires-Python: >=3.8
Requires-Dist: bs4
Requires-Dist: requests
